aircraft/__init__.py
aircraft/aircraft.py
aircraft/calculate_distance_of_aircraft.py
aircraft/exceptions.py
queryscanner/__init__.py
queryscanner/queryscanner.py
PiAware_Dump1090_Wrapper-1.0.0.dist-info/LICENSE
PiAware_Dump1090_Wrapper-1.0.0.dist-info/METADATA
PiAware_Dump1090_Wrapper-1.0.0.dist-info/WHEEL
PiAware_Dump1090_Wrapper-1.0.0.dist-info/top_level.txt
PiAware_Dump1090_Wrapper-1.0.0.dist-info/RECORD
