Metadata-Version: 2.1
Name: PiAware-Dump1090-Wrapper
Version: 1.0.0
Summary: A module for reading aircraft a PiAware device is sensing
Home-page: https://github.com/kc8/piawaredump1090wrapper
Author: Kyle Cooper
Author-email: kyle@cooperkyle.com
License: MIT
Platform: UNKNOWN
Requires-Dist: requests
